spreadconnect_python_sdk/__init__.py
spreadconnect_python_sdk/client.py
spreadconnect_python_sdk/exceptions.py
spreadconnect_python_sdk/api/__init__.py
spreadconnect_python_sdk/api/articles.py
spreadconnect_python_sdk/api/designs.py
spreadconnect_python_sdk/api/orders.py
spreadconnect_python_sdk/api/product_types.py
spreadconnect_python_sdk/api/stocks.py
spreadconnect_python_sdk/api/subscriptions.py
spreadconnect_python_sdk/endpoints/__init__.py
spreadconnect_python_sdk/endpoints/spod_endpoints.py
spreadconnect_python_sdk/http/__init__.py
spreadconnect_python_sdk/http/client.py
spreadconnect_python_sdk/models/__init__.py
spreadconnect_python_sdk/models/address.py
spreadconnect_python_sdk/models/articles.py
spreadconnect_python_sdk/models/categories.py
spreadconnect_python_sdk/models/common.py
spreadconnect_python_sdk/models/designs.py
spreadconnect_python_sdk/models/errors.py
spreadconnect_python_sdk/models/orders.py
spreadconnect_python_sdk/models/preview.py
spreadconnect_python_sdk/models/price.py
spreadconnect_python_sdk/models/products.py
spreadconnect_python_sdk/models/shipments.py
spreadconnect_python_sdk/models/shipping.py
spreadconnect_python_sdk/models/size_chart.py
spreadconnect_python_sdk/models/stocks.py
spreadconnect_python_sdk/models/subscriptions.py
spreadconnect_python_sdk/models/views.py
spreadconnect_python_sdk-1.0.1.dist-info/METADATA
spreadconnect_python_sdk-1.0.1.dist-info/WHEEL
spreadconnect_python_sdk-1.0.1.dist-info/entry_points.txt
spreadconnect_python_sdk-1.0.1.dist-info/licenses/LICENSE
spreadconnect_python_sdk-1.0.1.dist-info/RECORD
