Metadata-Version: 2.4
Name: spreadconnect-python-sdk
Version: 1.0.1
Summary: A SDK for Spreadconnect
Author-email: Konrad Hölzenbein <konrad@shop4fans.io>, Antonii Adamovych <antonii@shop4fans.io>
License-File: LICENSE
Requires-Python: >=3.12
Requires-Dist: httpx>=0.28.1
Requires-Dist: pydantic>=2.11.9
